cicada/__init__.py
cicada/active.py
cicada/additive.py
cicada/arithmetic.py
cicada/calculator.py
cicada/encoding.py
cicada/interactive.py
cicada/logger.py
cicada/przs.py
cicada/shamir.py
cicada/transcript.py
cicada/cli/__init__.py
cicada/cli/main.py
cicada/cli/perf.py
cicada/communicator/__init__.py
cicada/communicator/interface.py
cicada/communicator/socket/__init__.py
cicada/communicator/socket/connect.py
cicada_mpc-2.1.0.dist-info/entry_points.txt
cicada_mpc-2.1.0.dist-info/LICENSE
cicada_mpc-2.1.0.dist-info/WHEEL
cicada_mpc-2.1.0.dist-info/METADATA
cicada_mpc-2.1.0.dist-info/RECORD
