Metadata-Version: 2.1
Name: cicada-mpc
Version: 2.1.0
Summary: Flexible toolkit for fault tolerant secure multiparty computation.
Maintainer-email: "Timothy M. Shead" <tshead@sandia.gov>
Requires-Python: >=3.8
Classifier: Development Status :: 5 - Production/Stable
Classifier: Intended Audience :: Developers
Classifier: Intended Audience :: Education
Classifier: Intended Audience :: Information Technology
Classifier: Intended Audience :: Science/Research
Classifier: Natural Language :: English
Classifier: Programming Language :: Python :: 3
Classifier: Topic :: Communications
Classifier: Topic :: Scientific/Engineering
Classifier: Topic :: Security :: Cryptography
Classifier: Topic :: Utilities
Requires-Dist: netifaces
Requires-Dist: numpy
Requires-Dist: pynetstring
Requires-Dist: behave ; extra == "all"
Requires-Dist: coverage ; extra == "all"
Requires-Dist: hunter ; extra == "all"
Requires-Dist: ipython ; extra == "all"
Requires-Dist: nbsphinx ; extra == "all"
Requires-Dist: sphinx >= 3.5 ; extra == "all"
Requires-Dist: sphinx-argparse ; extra == "all"
Requires-Dist: sphinx-gallery < 0.11 ; extra == "all"
Requires-Dist: sphinx_rtd_theme ; extra == "all"
Requires-Dist: ipython ; extra == "doc"
Requires-Dist: nbsphinx ; extra == "doc"
Requires-Dist: sphinx >= 3.5 ; extra == "doc"
Requires-Dist: sphinx-argparse ; extra == "doc"
Requires-Dist: sphinx-gallery < 0.11 ; extra == "doc"
Requires-Dist: sphinx_rtd_theme ; extra == "doc"
Project-URL: Chat, https://github.com/cicada-mpc/cicada-mpc/discussions
Project-URL: Coverage, https://coveralls.io/r/cicada-mpc/cicada-mpc
Project-URL: Documentation, https://cicada-mpc.readthedocs.io
Project-URL: Issue Tracker, https://github.com/cicada-mpc/cicada-mpc/issues
Project-URL: Source, https://github.com/cicada-mpc/cicada-mpc
Provides-Extra: all
Provides-Extra: doc
